X2021NiukeHulianwangKaiguaGonglve/README.md
X2021NiukeHulianwangKaiguaGonglve/__init__.py
X2021NiukeHulianwangKaiguaGonglve/__main__.py
X2021NiukeHulianwangKaiguaGonglve/file.epub
X2021NiukeHulianwangKaiguaGonglve/index.html
X2021NiukeHulianwangKaiguaGonglve/css/__init__.py
X2021NiukeHulianwangKaiguaGonglve/css/annotations.css
X2021NiukeHulianwangKaiguaGonglve/css/main.css
X2021NiukeHulianwangKaiguaGonglve/css/normalize.css
X2021NiukeHulianwangKaiguaGonglve/css/popup.css
X2021NiukeHulianwangKaiguaGonglve/font/__init__.py
X2021NiukeHulianwangKaiguaGonglve/font/fontello.eot
X2021NiukeHulianwangKaiguaGonglve/font/fontello.svg
X2021NiukeHulianwangKaiguaGonglve/font/fontello.ttf
X2021NiukeHulianwangKaiguaGonglve/font/fontello.woff
X2021NiukeHulianwangKaiguaGonglve/img/__init__.py
X2021NiukeHulianwangKaiguaGonglve/img/annotator-glyph-sprite.png
X2021NiukeHulianwangKaiguaGonglve/img/annotator-icon-sprite.png
X2021NiukeHulianwangKaiguaGonglve/img/apple-touch-icon.png
X2021NiukeHulianwangKaiguaGonglve/img/cancelfullscreen.png
X2021NiukeHulianwangKaiguaGonglve/img/close.png
X2021NiukeHulianwangKaiguaGonglve/img/fullscreen.png
X2021NiukeHulianwangKaiguaGonglve/img/loader.gif
X2021NiukeHulianwangKaiguaGonglve/img/menu-icon.png
X2021NiukeHulianwangKaiguaGonglve/img/save.png
X2021NiukeHulianwangKaiguaGonglve/img/saved.png
X2021NiukeHulianwangKaiguaGonglve/img/settings-s.png
X2021NiukeHulianwangKaiguaGonglve/img/settings.png
X2021NiukeHulianwangKaiguaGonglve/img/star.png
X2021NiukeHulianwangKaiguaGonglve/js/__init__.py
X2021NiukeHulianwangKaiguaGonglve/js/epub.js
X2021NiukeHulianwangKaiguaGonglve/js/epub.min.js
X2021NiukeHulianwangKaiguaGonglve/js/epub.min.map
X2021NiukeHulianwangKaiguaGonglve/js/hooks.min.js
X2021NiukeHulianwangKaiguaGonglve/js/hooks.min.map
X2021NiukeHulianwangKaiguaGonglve/js/reader.js
X2021NiukeHulianwangKaiguaGonglve/js/reader.js.map
X2021NiukeHulianwangKaiguaGonglve/js/reader.min.js
X2021NiukeHulianwangKaiguaGonglve/js/reader.min.map
x2021_niuke_hulianwang_kaigua_gonglve-2024.3.6.0.dist-info/METADATA
x2021_niuke_hulianwang_kaigua_gonglve-2024.3.6.0.dist-info/WHEEL
x2021_niuke_hulianwang_kaigua_gonglve-2024.3.6.0.dist-info/entry_points.txt
x2021_niuke_hulianwang_kaigua_gonglve-2024.3.6.0.dist-info/top_level.txt
x2021_niuke_hulianwang_kaigua_gonglve-2024.3.6.0.dist-info/RECORD
